turingarena/__init__.py
turingarena/goals.py
turingarena/logging_helper.py
turingarena/metadata.py
turingarena/api/__init__.py
turingarena/api/aws_backend.py
turingarena/api/common.py
turingarena/api/dummy_impl.py
turingarena/api/dynamodb_events.py
turingarena/api/dynamodb_files.py
turingarena/api/evaluate.py
turingarena/api/git.py
turingarena/api/git_manager.py
turingarena/api/hypersh_api.py
turingarena/api/hypersh_evaluate.py
turingarena/api/hypersh_files.py
turingarena/api/lambda_proxy.py
turingarena/api/make_hypersh_files_request.py
turingarena/api/make_hypersh_request.py
turingarena/api/request.py
turingarena/api/s3_files.py
turingarena/api/serve.py
turingarena/api/wsgi_proxy.py
turingarena/driver/__init__.py
turingarena/driver/generator.py
turingarena/driver/language.py
turingarena/driver/server.py
turingarena/driver/visitors.py
turingarena/driver/client/__init__.py
turingarena/driver/client/commands.py
turingarena/driver/client/connection.py
turingarena/driver/client/exceptions.py
turingarena/driver/client/pipeboundary.py
turingarena/driver/client/process.py
turingarena/driver/client/processinfo.py
turingarena/driver/client/program.py
turingarena/driver/client/proxy.py
turingarena/driver/interface/__init__.py
turingarena/driver/interface/block.py
turingarena/driver/interface/callables.py
turingarena/driver/interface/common.py
turingarena/driver/interface/context.py
turingarena/driver/interface/diagnostics.py
turingarena/driver/interface/exceptions.py
turingarena/driver/interface/execution.py
turingarena/driver/interface/expressions.py
turingarena/driver/interface/grammar.py
turingarena/driver/interface/interface.py
turingarena/driver/interface/metadata.py
turingarena/driver/interface/nodes.py
turingarena/driver/interface/parser.py
turingarena/driver/interface/phase.py
turingarena/driver/interface/step.py
turingarena/driver/interface/variables.py
turingarena/driver/interface/statements/__init__.py
turingarena/driver/interface/statements/call.py
turingarena_dev-0.0.2.dev746.dist-info/METADATA
turingarena_dev-0.0.2.dev746.dist-info/WHEEL
turingarena_dev-0.0.2.dev746.dist-info/entry_points.txt
turingarena_dev-0.0.2.dev746.dist-info/top_level.txt
turingarena_dev-0.0.2.dev746.dist-info/RECORD
