Metadata-Version: 2.1
Name: turingarena-dev
Version: 0.0.2.dev746
Summary: Command Line Interface for TuringArena
Home-page: http://www.turingarena.org/
Author: TuringArena Group
Author-email: contact@turingarena.org
License: MPL 2.0
Project-URL: Source Code, https://github.com/turingarena/turingarena
Project-URL: Documentation, https://turingarena.readthedocs.io/
Project-URL: Bug Tracker, https://github.com/turingarena/turingarena/issues
Platform: UNKNOWN
Requires-Dist: bidict
Requires-Dist: boto3
Requires-Dist: coloredlogs
Requires-Dist: commonmark
Requires-Dist: lxml
Requires-Dist: psutil
Requires-Dist: seccomplite
Requires-Dist: pytest
Requires-Dist: requests
Requires-Dist: tatsu
Requires-Dist: toml
Requires-Dist: networkx
